azure_simple_email/__init__.py
azure_simple_email/azure_mail.py
azure_simple_email-0.1.9.dist-info/licenses/LICENSE
azure_simple_email-0.1.9.dist-info/METADATA
azure_simple_email-0.1.9.dist-info/WHEEL
azure_simple_email-0.1.9.dist-info/top_level.txt
azure_simple_email-0.1.9.dist-info/RECORD
