Metadata-Version: 2.4
Name: azure_simple_email
Version: 0.1.9
Summary: This is an experimental library to send email using Microsoft Graph API
Home-page: https://github.com/marcotn/azure_simple_email
Author: Marco Pavanelli
Author-email: marco.pavanelli@sasabz.it
Classifier: Programming Language :: Python :: 3
Classifier: License :: OSI Approved :: MIT License
Classifier: Operating System :: OS Independent
License-File: LICENSE
Requires-Dist: msal
Requires-Dist: requests
Dynamic: author
Dynamic: author-email
Dynamic: classifier
Dynamic: description
Dynamic: description-content-type
Dynamic: home-page
Dynamic: license-file
Dynamic: requires-dist
Dynamic: summary
